auto_easy/__init__.py
auto_easy/constant.py
auto_easy/global_log.py
auto_easy/__pycache__/__init__.cpython-39.pyc
auto_easy/base/__init__.py
auto_easy/base/find_color.py
auto_easy/base/windows.py
auto_easy/base/ai/__init__.py
auto_easy/base/ai/model_mgr_v2.py
auto_easy/base/ai/test_model_mgr_v2.py
auto_easy/base/ai/ai_ocr/__init__.py
auto_easy/base/ai/ai_ocr/ai_ocr.py
auto_easy/base/ai/ai_yolo/__init__.py
auto_easy/base/ai/ai_yolo/ai_yolo_v5.py
auto_easy/base/ai/superres/__init__.py
auto_easy/base/ai/superres/ai_supper_res.py
auto_easy/base/find_pic/__init__.py
auto_easy/base/find_pic/conf_base.py
auto_easy/base/find_pic/find_pic.py
auto_easy/base/find_pic/model.py
auto_easy/base/find_pic/pic_factory.py
auto_easy/base/find_pic/pic_handler.py
auto_easy/base/image/__init__.py
auto_easy/base/image/cvt.py
auto_easy/base/image/draw.py
auto_easy/base/image/process.py
auto_easy/core/__init__.py
auto_easy/core/core.py
auto_easy/core/win_ai.py
auto_easy/core/win_find_color.py
auto_easy/core/win_find_pic.py
auto_easy/core/win_monitor.py
auto_easy/core/win_ocr.py
auto_easy/core/win_show.py
auto_easy/core/win_supper_res.py
auto_easy/dag/__init__.py
auto_easy/dag/dag.py
auto_easy/dag/executor.py
auto_easy/dag/layer.py
auto_easy/dag/__pycache__/__init__.cpython-39.pyc
auto_easy/dag/__pycache__/executor.cpython-39.pyc
auto_easy/models/__init__.py
auto_easy/models/base_item.py
auto_easy/models/ctx.py
auto_easy/models/geometry.py
auto_easy/models/pic.py
auto_easy/utils/__init__.py
auto_easy/utils/cache_util.py
auto_easy/utils/cls_util.py
auto_easy/utils/common.py
auto_easy/utils/debug.py
auto_easy/utils/file_util.py
auto_easy/utils/list_util.py
auto_easy/utils/multi_thread.py
auto_easy/utils/queue_util.py
auto_easy/utils/time_util.py
test_pics/__init__.py
test_pics/core/__init__.py
test_pics/debug/__init__.py
test_pics/find_pic/__init__.py
tests/__init__.py
tests/init_test.py
tests/dag/__init__.py
tests/dag/test_dag.py
tests/dag/test_layer.py
auto_easy-0.1.23.dist-info/METADATA
auto_easy-0.1.23.dist-info/WHEEL
auto_easy-0.1.23.dist-info/top_level.txt
auto_easy-0.1.23.dist-info/RECORD
