Metadata-Version: 2.1
Name: auto_easy
Version: 0.1.23
Summary: make automated script development easier
Home-page: https://github.com/Jefung/auto_easy
Author: Jefung
Author-email: jefung865424525@gmail.com
Classifier: Programming Language :: Python :: 3
Classifier: License :: OSI Approved :: MIT License
Classifier: Operating System :: OS Independent
Requires-Python: >=3.9
